zato_client-3.2.1-py3.8-nspkg.pth
zato/client/__init__.py
zato_client-3.2.1.dist-info/METADATA
zato_client-3.2.1.dist-info/WHEEL
zato_client-3.2.1.dist-info/namespace_packages.txt
zato_client-3.2.1.dist-info/pbr.json
zato_client-3.2.1.dist-info/top_level.txt
zato_client-3.2.1.dist-info/RECORD
